minnetonka.py
minnetonka-0.0.1.dist-info/LICENSE
minnetonka-0.0.1.dist-info/METADATA
minnetonka-0.0.1.dist-info/WHEEL
minnetonka-0.0.1.dist-info/top_level.txt
minnetonka-0.0.1.dist-info/RECORD
