Metadata-Version: 2.1
Name: minnetonka
Version: 0.0.1
Summary: A Python package for business modeling and simulation
Home-page: https://github.com/bridgeland/minnetonka
Author: David Bridgeland
Author-email: dave@hangingsteel.com
License: UNKNOWN
Platform: UNKNOWN
Classifier: Development Status :: 3 - Alpha
Classifier: License :: OSI Approved :: Apache Software License
Requires-Python: >=3.6
Requires-Dist: numpy (>=1.15.2)
Requires-Dist: scipy (>=1.1.0)
